onvif_utilities/__init__.py
onvif_utilities/decorator.py
onvif_utilities/event.py
onvif_utilities/eventException.py
onvif_utilities/exceptions.py
onvif_utilities/information.py
onvif_utilities/main_class.py
onvif_utilities/onvif.py
onvif_utilities/parser.py
onvif_utilities/setting.py
onvif_utilities/wsdl.py
wsdl/__init__.py
wsdl/accesscontrol.wsdl
wsdl/actionengine.wsdl
wsdl/addressing
wsdl/advancedsecurity.wsdl
wsdl/analytics.wsdl
wsdl/analyticsdevice.wsdl
wsdl/b-2.xsd
wsdl/bf-2.xsd
wsdl/bw-2.wsdl
wsdl/deviceio.wsdl
wsdl/devicemgmt.wsdl
wsdl/display.wsdl
wsdl/doorcontrol.wsdl
wsdl/envelope
wsdl/events.wsdl
wsdl/imaging.wsdl
wsdl/include
wsdl/media.wsdl
wsdl/onvif.xsd
wsdl/ptz.wsdl
wsdl/r-2.xsd
wsdl/receiver.wsdl
wsdl/recording.wsdl
wsdl/remotediscovery.wsdl
wsdl/replay.wsdl
wsdl/rw-2.wsdl
wsdl/search.wsdl
wsdl/t-1.xsd
wsdl/types.xsd
wsdl/ws-addr.xsd
wsdl/ws-discovery.xsd
wsdl/xml.xsd
wsdl/xmlmime
onvif_utilities-0.3.4.dist-info/WHEEL
onvif_utilities-0.3.4.dist-info/METADATA
onvif_utilities-0.3.4.dist-info/RECORD
